bonch/__init__.py
bonch/common/AbstractClient.py
bonch/common/ISchedule.py
bonch/common/__init__.py
bonch/common/exception/__init__.py
bonch/common/model/DayScheduleModel.py
bonch/common/model/SubjectModel.py
bonch/common/model/SubjectTimeModel.py
bonch/common/model/SubjectType.py
bonch/common/model/WeekScheduleModel.py
bonch/common/model/__init__.py
bonch/common/week/WeekModel.py
bonch/common/week/__init__.py
bonch/common/week/number/StudyWeekNumberService.py
bonch/common/week/number/WeekNumberService.py
bonch/common/week/number/__init__.py
bonch/schedule/ScheduleBuilder.py
bonch/schedule/__init__.py
bonch/schedule/lk/Client.py
bonch/schedule/lk/Parser.py
bonch/schedule/lk/ScheduleFromLK.py
bonch/schedule/lk/__init__.py
bonch/schedule/site/Client.py
bonch/schedule/site/ScheduleFromSite.py
bonch/schedule/site/SiteScheduleType.py
bonch/schedule/site/__init__.py
bonch/schedule/site/groups/GroupListService.py
bonch/schedule/site/groups/__init__.py
bonch/schedule/site/model/FacultyModel.py
bonch/schedule/site/model/GroupItem.py
bonch/schedule/site/model/__init__.py
bonch/schedule/site/parser/TimeTableParser.py
bonch/schedule/site/parser/__init__.py
bonch_schedule-0.0.1.dist-info/METADATA
bonch_schedule-0.0.1.dist-info/WHEEL
bonch_schedule-0.0.1.dist-info/RECORD
