Metadata-Version: 2.1
Name: bonch-schedule
Version: 0.0.1
Summary: Schedule Module for bonch
Author: Никоноров Николай
Author-email: nnv@bitt.moe
Requires-Python: >=3.10,<4.0
Classifier: Programming Language :: Python :: 3
Classifier: Programming Language :: Python :: 3.10
Classifier: Programming Language :: Python :: 3.11
Classifier: Programming Language :: Python :: 3.12
Requires-Dist: beautifulsoup4 (==4.12.3)
Requires-Dist: bs4 (==0.0.2)
Requires-Dist: requests (==2.32.3)
